minimint/__init__.py
minimint/_version.py
minimint/bolom.py
minimint/mist_interpolator.py
minimint/utils.py
minimint-0.5.0.dist-info/METADATA
minimint-0.5.0.dist-info/WHEEL
minimint-0.5.0.dist-info/top_level.txt
minimint-0.5.0.dist-info/RECORD
