Metadata-Version: 2.4
Name: minimint
Version: 0.5.0
Summary: MIST Isochrone interpolation
Author-email: Sergey Koposov <skoposov@ed.ac.uk>
License: BSD
Project-URL: Homepage, http://github.com/segasai/minimint
Project-URL: Repository, http://github.com/segasai/minimint
Keywords: isochrone,interpolation
Classifier: Development Status :: 3 - Alpha
Classifier: Topic :: Utilities
Classifier: License :: OSI Approved :: BSD License
Requires-Python: >=3.8
Requires-Dist: numpy
Requires-Dist: scipy
Requires-Dist: astropy
